utm_referrer_parser/__init__.py
utm_referrer_parser/cache.py
utm_referrer_parser/parameters.py
utm_referrer_parser/parser.py
utm_referrer_parser/referrers.py
utm_referrer_parser/updater.py
utm_referrer_parser/webmetic.py
utm_referrer_parser/data/referers.yaml
utm_referrer_attribution_parser-0.1.4.dist-info/METADATA
utm_referrer_attribution_parser-0.1.4.dist-info/WHEEL
utm_referrer_attribution_parser-0.1.4.dist-info/licenses/LICENSE
utm_referrer_attribution_parser-0.1.4.dist-info/RECORD
