Metadata-Version: 2.4
Name: utm-referrer-attribution-parser
Version: 0.1.4
Summary: Modern Python library combining referrer parsing with tracking parameter extraction for web analytics
Project-URL: Homepage, https://webmetic.de
Project-URL: Repository, https://github.com/webmetic/utm-referrer-attribution-parser
Project-URL: Issues, https://github.com/webmetic/utm-referrer-attribution-parser/issues
Project-URL: Website, https://webmetic.de
Author-email: Webmetic <support@webmetic.de>
License-Expression: MIT
License-File: LICENSE
Keywords: analytics,attribution,referrer,tracking,utm
Classifier: Development Status :: 4 - Beta
Classifier: Intended Audience :: Developers
Classifier: License :: OSI Approved :: MIT License
Classifier: Programming Language :: Python :: 3
Classifier: Programming Language :: Python :: 3.8
Classifier: Programming Language :: Python :: 3.9
Classifier: Programming Language :: Python :: 3.10
Classifier: Programming Language :: Python :: 3.11
Classifier: Programming Language :: Python :: 3.12
Classifier: Topic :: Internet :: WWW/HTTP
Classifier: Topic :: Software Development :: Libraries :: Python Modules
Requires-Python: >=3.8
Requires-Dist: pyyaml>=6.0
Requires-Dist: requests>=2.25.0
Requires-Dist: tldextract>=3.1.0
Provides-Extra: dev
Requires-Dist: black>=22.0.0; extra == 'dev'
Requires-Dist: isort>=5.10.0; extra == 'dev'
Requires-Dist: mypy>=1.0.0; extra == 'dev'
Requires-Dist: pytest-cov>=4.0.0; extra == 'dev'
Requires-Dist: pytest>=7.0.0; extra == 'dev'
Requires-Dist: ruff>=0.1.0; extra == 'dev'
